blender_plot/__init__.py
blender_plot/materials.blend
blender_plot/materials/__init__.py
blender_plot/materials/base.py
blender_plot/materials/collection.py
blender_plot/materials/color.py
blender_plot/materials/gradient.py
blender_plot/materials/solid.py
blender_plot/materials/static.py
blender_plot/plots/__init__.py
blender_plot/plots/scatter.py
blender_plot/scenes/__init__.py
blender_plot/scenes/base.py
blender_plot/scenes/default.py
blender_plot/utils/__init__.py
blender_plot/utils/core.py
blender_plot-0.0.3.dist-info/LICENSE
blender_plot-0.0.3.dist-info/METADATA
blender_plot-0.0.3.dist-info/WHEEL
blender_plot-0.0.3.dist-info/top_level.txt
blender_plot-0.0.3.dist-info/RECORD
