Metadata-Version: 2.1
Name: blender-plot
Version: 0.0.3
Summary: A High-Level Plotting Interface for Blender in Python.
Author-email: Lars Kuehmichel <lars.kuehmichel@stud.uni-heidelberg.de>, Philipp Koehler <philipp@pvplanet.net>
License: GNU GENERAL PUBLIC LICENSE
Project-URL: Homepage, https://github.com/LarsKue/blender-plot
Project-URL: Bug Tracker, https://github.com/LarsKue/blender-plot/issues
Classifier: Programming Language :: Python :: 3
Classifier: License :: OSI Approved :: GNU General Public License v3 (GPLv3)
Classifier: Operating System :: OS Independent
Requires-Python: ~=3.10
License-File: LICENSE
Requires-Dist: bpy (~=3.4.0)
Requires-Dist: fake-bpy-module-latest
Provides-Extra: dev
Requires-Dist: jupyterlab (~=3.5.0) ; extra == 'dev'
Requires-Dist: numpy (~=1.23.5) ; extra == 'dev'
Requires-Dist: matplotlib (~=3.6.2) ; extra == 'dev'
Provides-Extra: test
Requires-Dist: coverage (~=6.5.0) ; extra == 'test'
Requires-Dist: pytest (~=7.2.0) ; extra == 'test'
Requires-Dist: mypy (~=0.991) ; extra == 'test'
